{
  "indonesia": [
    { "name": "80s Radio Hits", "url": "https://stream-037.zeno.fm/05eu8medd3quv?zs=nn3VmkBWSbuGUmPs4VtkyQ" },
    { "name": "9020 FB FM Purwakarta", "url": "https://ssg.streamingmurah.com:8434/stream" },
    { "name": "Ardan Radio", "url": "https://n13.rcs.revma.com/ugpyzu9n5k3vv" },
    { "name": "B Radio Bandung", "url": "https://n08.rcs.revma.com/9yp8b9pd6k3vv" },
    { "name": "Bahana Fm", "url": "https://s1.cloudmu.id/listen/bahana_fm/stream" },
    { "name": "Brava FM", "url": "https://n08.radiojar.com/5k7t0rq3bnzuv" },
    { "name": "Campur sari", "url": "https://a8.siar.us/listen/campursari/stream" },
    { "name": "Cosmopolitan", "url": "http://stream.radiojar.com/u7d8heq3bnzuv" },
    { "name": "Dahlia FM", "url": "https://svara-stream.radioddns.net/bandung_dahliafm" },
    { "name": "Delta FM", "url": "https://s1.cloudmu.id/listen/delta_fm/stream" },
    { "name": "DFM Radio Jakarta", "url": "https://i.klikhost.com/9000/stream" },
    { "name": "Elgangga", "url": "https://b.alhastream.com:5140/radio?_ic2=1715794029661" },
    { "name": "Elshinta", "url": "https://stream-ssl.arenastreaming.com:8000/jakarta" },
    { "name": "Female Radio", "url": "https://s1.cloudmu.id/listen/female_radio/stream" },
    { "name": "Flamboyan FM", "url": "https://i.klikhost.com/8236/stream" },
    { "name": "Gajahmada FM", "url": "https://server.radioimeldafm.co.id/radio/8040/gajahmadafm" },
    { "name": "Gema Surya FM", "url": "https://r5.siar.us:9420/mp3.mp3" },
    { "name": "Gen FM 98.7 Jakarta", "url": "https://wz.mari.co.id:1936/web_genfm/genfm/playlist.m3u8" },
    { "name": "Gen FM Surabaya", "url": "https://wz.mari.co.id:1936/web_genfmsby/gensbyic.stream/playlist.m3u8" },
    { "name": "Global Radio Jakarta", "url": "https://proxy.rctiplus.com/?name=http://111.119.207.125:8064/;" },
    { "name": "Hard Rock", "url": "https://n08.radiojar.com/7csmg90fuqruv.mp3?rj-tok=AAABh99NlQQAnnz8d1obRSB4IQ&rj-ttl=5" },
    { "name": "Hits Memories", "url": "https://onlineradiobox.com/ping/id.hitsmemories" },
    { "name": "HOT FM", "url": "https://wz.mari.co.id:1936/web_hotfm/hotfm/playlist.m3u8" },
    { "name": "I-Dream Radio", "url": "https://void.idserverhost.com:8010/;" },
    { "name": "Idola fm semarang", "url": "https://server.radioidola.com:8880/idolafm" },
    { "name": "IMI radio", "url": "https://a1.siar.us/listen/imiradio/stream" },
    { "name": "Imelda FM", "url": "https://server.radioimeldafm.co.id:8030/imeldafm" },
    { "name": "iradio Bandung", "url": "https://n0d.radiojar.com/u6ppe6hswk8uv?rj-ttl=5&rj-tok=AAABh91unGUAQWkoQMxUWz6UvQ" },
    { "name": "iradio jakarta", "url": "https://n13.radiojar.com/4ywdgup3bnzuv" },
    { "name": "Jak 101 FM", "url": "https://wz.mari.co.id:1936/web_jakfm/jakfm/playlist.m3u8" },
    { "name": "Kajian Islam", "url": "https://stream-002.zeno.fm/ge2ekgd7f18uv?zs=Y3dB0G3tQ1WBU2tWIwzIJg" },
    { "name": "KIS FM Semarang", "url": "http://123.255.201.126:8020/kisfm" },
    { "name": "KISI FM", "url": "https://live.kisifm.com/listen/kisifm/kisifm" },
    { "name": "Kiss FM", "url": "https://ic.mari.co.id:8443/kisfm" },
    { "name": "Loker Musik Indonesia", "url": "https://stream.lokermusik.com/listen/lokermusik/lokermusik" },
    { "name": "Media fm", "url": "http://streaming.radiomediafm.com:8400/;stream.nsv" },
    { "name": "Medan fm", "url": "https://live.medanfm.id/medanfm.ogg" },
    { "name": "Megaswara Bogor", "url": "https://server.adyadigitalteknologi.com:8010/1" },
    { "name": "Merdeka fm", "url": "http://streaming.merdekafm.com:8020/;stream.nsv" },
    { "name": "Mendhut FM", "url": "http://c4.siar.us:8790/stream" },
    { "name": "Mettaswara", "url": "https://mettaswara.com:8700/indo" },
    { "name": "Mettaswara Dangdut", "url": "https://mettaswara.com:8700/d4d" },
    { "name": "MGT FM", "url": "https://s1.gntr.net/listen/mgtradio/mgtradio" },
    { "name": "Motion Radio Jakarta", "url": "https://cast3.asurahosting.com/proxy/radios22/stream" },
    { "name": "Most FM", "url": "https://ic.mari.co.id:8443/mostfm" },
    { "name": "MQFM Bandung", "url": "https://mqfmstreaming.kamil.web.id/;" },
    { "name": "Muara dss", "url": "https://ssg.streamingmurah.com:8668/;?1683089782130" },
    { "name": "OZ Bandung", "url": "https://streaming.ozradio.id:8443/ozbandung" },
    { "name": "Paramuda FM", "url": "https://i.klikhost.com/8332/;" },
    { "name": "PASS FM Bandung", "url": "https://stream-174.zeno.fm/w70fp14bs18uv" },
    { "name": "Pop FM", "url": "https://i.klikhost.com/8272/stream" },
    { "name": "Prambors FM", "url": "https://s2.cloudmu.id/listen/prambors/stream" },
    { "name": "Radio BOSS FM", "url": "https://a7.siar.us/listen/radiobossfm/stream" },
    { "name": "Radio Budi Luhur", "url": "https://onlineradiobox.com/ping/id.budiluhur" },
    { "name": "Radio Cakra Bandung", "url": "https://stream-156.zeno.fm/yoengdcdzyauv" },
    { "name": "Radio CBB", "url": "https://stream01-ssl.arenastreaming.com:8056/live" },
    { "name": "Radio CMN", "url": "https://stream.coolkas.com/radio/8160/radiocmn" },
    { "name": "Radio Cosmo", "url": "http://scg.streamingmurah.com:8074/stream" },
    { "name": "Radio Dangdut Indonesia", "url": "https://stream.roov.id:8062/stream" },
    { "name": "Radio Galuh", "url": "https://stream.yaomiakba.com/galuhfm" },
    { "name": "Radio Idola Semarang", "url": "https://stream.radioidola.com/listen/idolafm/live" },
    { "name": "Radio Muara", "url": "http://45.64.97.82:8778/;" },
    { "name": "Radio Musik Indonesia", "url": "https://stream-034.zeno.fm/727gv3qrt5quv?zs=q5wF9_yCQgy8tFIM3phRmg" },
    { "name": "Radio Rodja", "url": "https://radioislamindonesia.com/rodja-low.mp3" },
    { "name": "Raka FM", "url": "https://cast2.my-control-panel.com/proxy/radioso5/stream" },
    { "name": "Rama FM Bandung", "url": "https://i.klikhost.com/8330/;" },
    { "name": "RAS FM", "url": "https://i.klikhost.com/9006/stream/1/" },
    { "name": "RRI Pro 1 Jakarta", "url": "https://stream-node1.rri.co.id/streaming/25/9025/rrijakartapro1.mp3" },
    { "name": "RRI Pro 2 Jakarta", "url": "https://stream-node1.rri.co.id/streaming/25/9025/rrijakartapro2.mp3" },
    { "name": "RRI Pro 3 Yogyakarta", "url": "https://stream-node0.rri.co.id/streaming/14/9014/kbrn.mp3" },
    { "name": "RRI Pro 4 Jakarta", "url": "https://stream-node1.rri.co.id/streaming/25/9025/rrijakartapro4.mp3" },
    { "name": "Simfoni FM", "url": "http://i.klikhost.com:9160/;rojer.mp3" },
    { "name": "Smart FM Jakarta", "url": "https://cast2.my-control-panel.com/proxy/radioso3/stream" },
    { "name": "Smooth FM Jakarta", "url": "https://svara-stream.radioddns.net/jakarta_smoothfm_mp3" },
    { "name": "Sonora FM Jakarta", "url": "https://cast1.my-control-panel.com/proxy/radioso1/live" },
    { "name": "Suara Giri FM", "url": "http://streaming.girifm.com:8010/;" },
    { "name": "Suara Soneta Radio", "url": "https://a2.siar.us/listen/suarasoneta/radio.mp3" },
    { "name": "Suara surabaya", "url": "https://c5.siar.us:8000/stream" },
    { "name": "Sunda Radio", "url": "https://sundaradio.com/live/sundaradio" },
    { "name": "Swara semarang", "url": "https://server.radioimeldafm.co.id/radio/8010/swarasemarang" },
    { "name": "Tangerang radio", "url": "https://rl.tangerank.my.id/swara" },
    { "name": "Trax FM", "url": "https://n0a.radiojar.com/rrqf78p3bnzuv?rj-ttl=5&rj-tok=AAABh9163ogAt_w8aT7VUcRuAA" },
    { "name": "Trijaya FM Jakarta", "url": "http://202.147.199.101:8000/;" },
    { "name": "Urban FM Bandung", "url": "https://a1.siar.us/listen/urbanradio/stream" },
    { "name": "Wijaya FM", "url": "http://wijayafm.onlivestreaming.net:9880/stream?" },
    { "name": "Z 99.9 FM", "url": "https://svara-stream.radioddns.net/jakarta_z999fm_aac" }
  ],
  "international": [
    { "name": "BBC Radio 1", "url": "http://stream.live.vc.bbcmedia.co.uk/bbc_radio_one", "country": "United Kingdom" },
    { "name": "BBC Radio 2", "url": "http://stream.live.vc.bbcmedia.co.uk/bbc_radio_two", "country": "United Kingdom" },
    { "name": "BBC Radio 4", "url": "http://stream.live.vc.bbcmedia.co.uk/bbc_radio_fourfm", "country": "United Kingdom" },
    { "name": "Kiss FM UK", "url": "http://stream.planetradio.co.uk/kiss100.aac", "country": "United Kingdom" },
    { "name": "Capital FM London", "url": "http://media-ice.musicradio.com/CapitalMP3", "country": "United Kingdom" },
    { "name": "Heart London", "url": "http://media-ice.musicradio.com/HeartLondonMP3", "country": "United Kingdom" },
    { "name": "Smooth Radio UK", "url": "http://media-ice.musicradio.com/SmoothUKMP3", "country": "United Kingdom" },
    { "name": "TalkSport UK", "url": "http://radio.talksport.com/stream", "country": "United Kingdom" },
    { "name": "Absolute Radio", "url": "http://stream.planetradio.co.uk/absoluteradio.mp3", "country": "United Kingdom" },
    { "name": "LBC London", "url": "http://media-ice.musicradio.com/LBCUKMP3", "country": "United Kingdom" },

    { "name": "NPR News", "url": "https://npr-ice.streamguys1.com/live.mp3", "country": "United States" },
    { "name": "KEXP Seattle", "url": "http://live-mp3-128.kexp.org/kexp128.mp3", "country": "United States" },
    { "name": "Hot 97 New York", "url": "http://stream.revma.ihrhls.com/zc1469", "country": "United States" },
    { "name": "Power 106 LA", "url": "http://ice8.securenetsystems.net/KPWR", "country": "United States" },
    { "name": "KIIS FM Los Angeles", "url": "http://stream.revma.ihrhls.com/zc146", "country": "United States" },
    { "name": "Z100 New York", "url": "http://stream.revma.ihrhls.com/zc1467", "country": "United States" },
    { "name": "WFAN Sports Radio", "url": "http://stream.am570sports.com/stream", "country": "United States" },
    { "name": "KROQ Los Angeles", "url": "http://stream.revma.ihrhls.com/zc1465", "country": "United States" },
    { "name": "WBLS 107.5 NY", "url": "http://ice8.securenetsystems.net/WBLS", "country": "United States" },
    { "name": "iHeartRadio Hits", "url": "http://stream.revma.ihrhls.com/zc1463", "country": "United States" },

    { "name": "Antenne Bayern", "url": "http://mp3channels.webradio.antenne.de/antenne", "country": "Germany" },
    { "name": "Radio Hamburg", "url": "http://stream.radiohamburg.de/live/mp3-192", "country": "Germany" },
    { "name": "1Live (WDR)", "url": "http://wdr-1live-live.icecast.wdr.de/wdr/1live/live/mp3/128/stream.mp3", "country": "Germany" },
    { "name": "Deutschlandfunk", "url": "http://st01.dlf.de/dlf/01/128/mp3/stream.mp3", "country": "Germany" },
    { "name": "SWR3", "url": "http://mp3-live.swr3.de/swr3_m.m3u", "country": "Germany" },
    { "name": "Radio Regenbogen", "url": "http://streams.regenbogen.de/live/mp3-192/streams.regenbogen.de/", "country": "Germany" },
    { "name": "Energy Berlin", "url": "http://scast.nrj.de/berlin", "country": "Germany" },
    { "name": "Radio NRW", "url": "http://stream.lokalradio.nrw/stream", "country": "Germany" },
    { "name": "MDR Jump", "url": "http://mdr-284320-0.cast.mdr.de/mdr/284320/0/mp3/high/stream.mp3", "country": "Germany" },
    { "name": "FFH Radio", "url": "http://streams.ffh.de/ffhchannels/aac/hq", "country": "Germany" },

    { "name": "NRJ France", "url": "http://cdn.nrjaudio.fm/audio1/fr/30001/mp3_128.mp3", "country": "France" },
    { "name": "Fun Radio France", "url": "http://streaming.radio.funradio.fr/fun-1-48-192", "country": "France" },
    { "name": "RTL France", "url": "http://streaming.radio.rtl.fr/rtl-1-44-96", "country": "France" },
    { "name": "Europe 1", "url": "http://e1-live-mp3-128.scdn.arkena.com/europe1.mp3", "country": "France" },
    { "name": "RMC Info Talk", "url": "http://rmc.bfmtv.com/rmcinfo-mp3", "country": "France" },
    { "name": "Radio Nova", "url": "http://nova-mp3-128.scdn.arkena.com/nova.mp3", "country": "France" },
    { "name": "Chérie FM", "url": "http://cdn.nrjaudio.fm/adwz1/fr/30401/mp3_128.mp3", "country": "France" },
    { "name": "Skyrock Paris", "url": "http://icecast.skyrock.net/s/natio_mp3_128k", "country": "France" },
    { "name": "Radio Classique", "url": "http://radioclassique.ice.infomaniak.ch/radioclassique-high.mp3", "country": "France" },
    { "name": "FIP Radio", "url": "http://direct.fipradio.fr/live/fip-midfi.mp3", "country": "France" },

    { "name": "NHK Radio 1", "url": "http://nhkr1stream.nhk.jp/hls/live/2003456/nhkr1/master.m3u8", "country": "Japan" },
    { "name": "NHK Radio 2", "url": "http://nhkr2stream.nhk.jp/hls/live/2003457/nhkr2/master.m3u8", "country": "Japan" },
    { "name": "Tokyo FM", "url": "http://radiko.jp/live/FMT", "country": "Japan" },
    { "name": "FM Yokohama", "url": "http://radiko.jp/live/YFM", "country": "Japan" },
    { "name": "FM802 Osaka", "url": "http://radiko.jp/live/802", "country": "Japan" },
    { "name": "ZIP-FM Nagoya", "url": "http://radiko.jp/live/ZIP-FM", "country": "Japan" },
    { "name": "J-Wave Tokyo", "url": "http://radiko.jp/live/FMJ", "country": "Japan" },
    { "name": "NHK FM", "url": "http://nhkfmstream.nhk.jp/hls/live/2003458/nhkfm/master.m3u8", "country": "Japan" },
    { "name": "InterFM Tokyo", "url": "http://radiko.jp/live/INT", "country": "Japan" },
    { "name": "Radio NIKKEI", "url": "http://radiko.jp/live/RN1", "country": "Japan" },

    { "name": "KBS 1 Radio", "url": "http://kbsradio1.stream", "country": "South Korea" },
    { "name": "KBS Cool FM", "url": "http://kbsradio2.stream", "country": "South Korea" },
    { "name": "SBS Power FM", "url": "http://sbs.co.kr/powerfm", "country": "South Korea" },
    { "name": "MBC FM4U", "url": "http://mbc.fm4u.stream", "country": "South Korea" },
    { "name": "TBS eFM Seoul", "url": "http://tbsefm.stream", "country": "South Korea" },
    { "name": "Arirang Radio", "url": "http://arirangradio.stream", "country": "South Korea" },
    { "name": "CBS Music FM", "url": "http://cbsfm.stream", "country": "South Korea" },
    { "name": "YTN News FM", "url": "http://ytnfm.stream", "country": "South Korea" },
    { "name": "EBS FM", "url": "http://ebsfm.stream", "country": "South Korea" },
    { "name": "KBS World Radio", "url": "http://world.kbs.co.kr/stream", "country": "South Korea" },

    { "name": "Triple J", "url": "http://live-radio01.mediahubaustralia.com/2TJW/mp3/", "country": "Australia" },
    { "name": "2GB Sydney", "url": "http://live-radio01.mediahubaustralia.com/2GBW/mp3/", "country": "Australia" },
    { "name": "ABC News Radio", "url": "http://live-radio01.mediahubaustralia.com/NLW/mp3/", "country": "Australia" },
    { "name": "KIIS 106.5 Sydney", "url": "http://icy.ihrcast.arn.com.au/au_002_icy", "country": "Australia" },
    { "name": "Nova 96.9 Sydney", "url": "http://stream.novaentertainment.com.au/nova969", "country": "Australia" },
    { "name": "Fox FM Melbourne", "url": "http://stream.novaentertainment.com.au/fox", "country": "Australia" },
    { "name": "Triple M Sydney", "url": "http://icy.ihrcast.arn.com.au/au_001_icy", "country": "Australia" },
    { "name": "Gold 104.3 Melbourne", "url": "http://stream.novaentertainment.com.au/gold1043", "country": "Australia" },
    { "name": "2Day FM Sydney", "url": "http://icy.ihrcast.arn.com.au/au_003_icy", "country": "Australia" },
    { "name": "Smooth FM 95.3", "url": "http://stream.novaentertainment.com.au/smooth953", "country": "Australia" },

    { "name": "Radio Italia", "url": "http://icecast.unitedradio.it/radioitalia", "country": "Italy" },
    { "name": "Radio 105", "url": "http://icecast.unitedradio.it/Radio105", "country": "Italy" },
    { "name": "RDS 100% Grandi Successi", "url": "http://stream1.rds.it:8000/rds64", "country": "Italy" },
    { "name": "Radio Deejay", "url": "http://icecast.unitedradio.it/deejay.mp3", "country": "Italy" },
    { "name": "Radio Capital", "url": "http://icecast.unitedradio.it/capital.mp3", "country": "Italy" },
    { "name": "RTL 102.5", "url": "http://streamingv2.shoutcast.com/rtl-1025", "country": "Italy" },
    { "name": "Radio Monte Carlo", "url": "http://icecast.unitedradio.it/rmc.mp3", "country": "Italy" },
    { "name": "Radio Kiss Kiss", "url": "http://ice07.fluidstream.net/KissKiss.mp3", "country": "Italy" },
    { "name": "Virgin Radio Italy", "url": "http://icecast.unitedradio.it/Virgin.mp3", "country": "Italy" },
    { "name": "Radio Subasio", "url": "http://onair18.xdevel.com:8066", "country": "Italy" },

    { "name": "Los 40 Principales", "url": "http://streaming.prisasd.com/LOS40.mp3", "country": "Spain" },
    { "name": "Cadena SER", "url": "http://streaming.prisasd.com/SER.mp3", "country": "Spain" },
    { "name": "COPE Madrid", "url": "http://195.55.74.198/cope/madrid/mp3", "country": "Spain" },
    { "name": "Radio Nacional de España", "url": "http://rtve.stream/rne1.mp3", "country": "Spain" },
    { "name": "Rock FM Spain", "url": "http://rockfm.stream/rockfm.mp3", "country": "Spain" },
    { "name": "Cadena 100", "url": "http://cadena100-mp3.flumotion.com/cadena100.mp3", "country": "Spain" },
    { "name": "Onda Cero", "url": "http://icecast-streaming.antena3.com/ondacero", "country": "Spain" },
    { "name": "Europa FM Spain", "url": "http://europafm-mp3.flumotion.com/europafm.mp3", "country": "Spain" },
    { "name": "Kiss FM Spain", "url": "http://kissfm.kissfmradio.cires21.com/kissfm.mp3", "country": "Spain" },
    { "name": "Maxima FM", "url": "http://195.55.74.210/rtve/maximafm.mp3", "country": "Spain" },

    { "name": "Radio Globo Rio", "url": "http://streaming.radioglobo.globo.com/live", "country": "Brazil" },
    { "name": "Jovem Pan FM", "url": "http://streaming.jovempan.com.br/jp", "country": "Brazil" },
    { "name": "Radio Gaucha", "url": "http://gauchazh-rb.rbsdirect.com.br/live", "country": "Brazil" },
    { "name": "BandNews FM", "url": "http://stream.bandnewsfm.com.br/live", "country": "Brazil" },
    { "name": "CBN Radio", "url": "http://streaming.cbn.globoradio.globo.com/live", "country": "Brazil" },
    { "name": "Alpha FM São Paulo", "url": "http://alphafm.stream/alphafm.mp3", "country": "Brazil" },
    { "name": "Transamérica Pop", "url": "http://stream.transanet.com.br/pop", "country": "Brazil" },
    { "name": "Radio Mix FM", "url": "http://streaming.mixfm.com.br/live", "country": "Brazil" },
    { "name": "Radio Metropolitana FM", "url": "http://metropolitana.stream/stream.mp3", "country": "Brazil" },
    { "name": "Energia 97 FM", "url": "http://energia97.stream/stream.mp3", "country": "Brazil" },

    { "name": "CBC Radio One Toronto", "url": "http://cbc_r1_toronto.stream", "country": "Canada" },
    { "name": "CBC Radio 2", "url": "http://cbc_r2_toronto.stream", "country": "Canada" },
    { "name": "CHUM FM Toronto", "url": "http://bellmediachumfm.leanstream.co/CHUMFM", "country": "Canada" },
    { "name": "Boom 97.3 Toronto", "url": "http://newcap.leanstream.co/CKFMFM", "country": "Canada" },
    { "name": "Z103.5 Toronto", "url": "http://z1035.streamon.fm:8000/Z1035-48k.aac", "country": "Canada" },
    { "name": "Virgin Radio Montreal", "url": "http://stream.bellmedia.radio/virginradio", "country": "Canada" },
    { "name": "CKNW 980 Vancouver", "url": "http://live.am980.ca/CKNWAM", "country": "Canada" },
    { "name": "The Edge 102.1 Toronto", "url": "http://newcap.leanstream.co/CIND", "country": "Canada" },
    { "name": "Q107 Toronto", "url": "http://rogers-hls.leanstream.co/rogers/q107.mp3", "country": "Canada" },
    { "name": "KISS 92.5 Toronto", "url": "http://newcap.leanstream.co/CKISFM", "country": "Canada" }
  ]
}
